django33_cors/__init__.py
django33_cors/apps.py
django33_cors/checks.py
django33_cors/conf.py
django33_cors/defaults.py
django33_cors/middleware.py
django33_cors/signals.py
django33_cors-0.1.0.dist-info/LICENSE
django33_cors-0.1.0.dist-info/METADATA
django33_cors-0.1.0.dist-info/WHEEL
django33_cors-0.1.0.dist-info/RECORD
